srq_score_wheel/__init__.py
srq_score_wheel/app_io/__init__.py
srq_score_wheel/app_io/compatible_cascade.py
srq_score_wheel/app_io/load_cascade.py
srq_score_wheel/cascade/__init__.py
srq_score_wheel/cascade/features/__init__.py
srq_score_wheel/cascade/features/model.py
srq_score_wheel/cascade/features/scale.py
srq_score_wheel/cascade/features/topics.py
srq_score_wheel/cascade/features/word2vec.py
srq_score_wheel/cascade/features/words.py
srq_score_wheel/cascade/models/__init__.py
srq_score_wheel/cascade/models/aux.py
srq_score_wheel/cascade/models/predictions.py
srq_score_wheel/cascade/reflections/__init__.py
srq_score_wheel/cascade/reflections/content.py
srq_score_wheel-1.0.0.dist-info/METADATA
srq_score_wheel-1.0.0.dist-info/WHEEL
srq_score_wheel-1.0.0.dist-info/top_level.txt
srq_score_wheel-1.0.0.dist-info/RECORD
