Metadata-Version: 2.1
Name: srq-score-wheel
Version: 1.0.0
Summary: Python package for model endpoint
Author: Sown To Grow
Author-email: developers@sowntogrow.com
Classifier: Programming Language :: Python :: 3.9
